{
  "carryovers": [
    {
      "carryoverAmount": 118043,
      "carryover": "$118,043",
      "wagertype": "Super High Five Jackpot",
      "track": "Woodbine",
      "date": "Oct 27",
      "ndate": 20241027
    },
    {
      "carryoverAmount": 48484,
      "carryover": "$48,484",
      "wagertype": "Pick 5",
      "track": "Gulfstream Park",
      "date": "Oct 27",
      "ndate": 20241027
    },
    {
      "carryoverAmount": 28179,
      "carryover": "$28,179",
      "wagertype": "Pick 5",
      "track": "Horseshoe",
      "date": "Oct 28",
      "ndate": 20241028
    },
    {
      "carryoverAmount": 23488,
      "carryover": "$23,488",
      "wagertype": "Super High Five Jackpot",
      "track": "Lone Star",
      "date": "Oct 31",
      "ndate": 20241031
    },
    {
      "carryoverAmount": 22256,
      "carryover": "$22,256",
      "wagertype": "Pick 5 Jackpot",
      "track": "Parx Racing",
      "date": "Oct 28",
      "ndate": 20241028
    },
    {
      "carryoverAmount": 20917,
      "carryover": "$20,917",
      "wagertype": "Pick 6 Jackpot",
      "track": "Charles Town",
      "date": "Oct 30",
      "ndate": 20241030
    },
    {
      "carryoverAmount": 18300,
      "carryover": "$18,300",
      "wagertype": "Pick 6 Jackpot",
      "track": "Woodbine",
      "date": "Oct 27",
      "ndate": 20241027
    },
    {
      "carryoverAmount": 13777,
      "carryover": "$13,777",
      "wagertype": "Pick 6 Jackpot",
      "track": "Laurel Park",
      "date": "Oct 27",
      "ndate": 20241027
    },
    {
      "carryoverAmount": 13200,
      "carryover": "$13,200",
      "wagertype": "3x3",
      "track": "Santa Anita",
      "date": "Oct 27",
      "ndate": 20241027
    },
    {
      "carryoverAmount": 10000,
      "carryover": "$10,000",
      "wagertype": "Pick 6",
      "track": "Los Alamitos",
      "date": "Oct 27",
      "ndate": 20241027
    },
    {
      "carryoverAmount": 9425,
      "carryover": "$9,425",
      "wagertype": "Pick 5",
      "track": "Finger Lakes",
      "date": "Oct 28",
      "ndate": 20241028
    },
    {
      "carryoverAmount": 3596,
      "carryover": "$3,596",
      "wagertype": "Super High Five",
      "track": "Pleasanton",
      "date": "Oct 27",
      "ndate": 20241027
    },
    {
      "carryoverAmount": 3422,
      "carryover": "$3,422",
      "wagertype": "Pick 7",
      "track": "Fanduel",
      "date": "Oct 29",
      "ndate": 20241029
    },
    {
      "carryoverAmount": 3310,
      "carryover": "$3,310",
      "wagertype": "Super High Five",
      "track": "Gulfstream Park",
      "date": "Oct 27",
      "ndate": 20241027
    },
    {
      "carryoverAmount": 2973,
      "carryover": "$2,973",
      "wagertype": "Super High Five",
      "track": "Horseshoe",
      "date": "Oct 28",
      "ndate": 20241028
    },
    {
      "carryoverAmount": 2262,
      "carryover": "$2,262",
      "wagertype": "Super High Five",
      "track": "Horseshoe",
      "date": "Oct 28",
      "ndate": 20241028
    },
    {
      "carryoverAmount": 1851,
      "carryover": "$1,851",
      "wagertype": "Pick 6",
      "track": "Finger Lakes",
      "date": "Oct 28",
      "ndate": 20241028
    },
    {
      "carryoverAmount": 1820,
      "carryover": "$1,820",
      "wagertype": "Super High Five Jackpot",
      "track": "Penn National",
      "date": "Oct 30",
      "ndate": 20241030
    },
    {
      "carryoverAmount": 1346,
      "carryover": "$1,346",
      "wagertype": "Pick 6 Jackpot",
      "track": "Pleasanton",
      "date": "Oct 27",
      "ndate": 20241027
    },
    {
      "carryoverAmount": 1026,
      "carryover": "$1,026",
      "wagertype": "Super High Five",
      "track": "Mountaineer",
      "date": "Oct 27",
      "ndate": 20241027
    },
    {
      "carryoverAmount": 334,
      "carryover": "$334",
      "wagertype": "Super High Five Jackpot",
      "track": "Century Downs",
      "date": "Oct 27",
      "ndate": 20241027
    }
  ]
}
