{
  "carryovers": [
    {
      "carryoverAmount": 172752,
      "carryover": "$172,752",
      "wagertype": "Super High Five Jackpot",
      "track": "Woodbine",
      "date": "Oct 22",
      "ndate": 20231022
    },
    {
      "carryoverAmount": 110817,
      "carryover": "$110,817",
      "wagertype": "Pick 5 Jackpot",
      "track": "Parx Racing",
      "date": "Oct 23",
      "ndate": 20231023
    },
    {
      "carryoverAmount": 104168,
      "carryover": "$104,168",
      "wagertype": "Pick 5 Jackpot",
      "track": "Parx Racing",
      "date": "Oct 23",
      "ndate": 20231023
    },
    {
      "carryoverAmount": 19438,
      "carryover": "$19,438",
      "wagertype": "Pick 5",
      "track": "Laurel Park",
      "date": "Oct 22",
      "ndate": 20231022
    },
    {
      "carryoverAmount": 13975,
      "carryover": "$13,975",
      "wagertype": "Pick 7",
      "track": "Fanduel",
      "date": "Oct 24",
      "ndate": 20231024
    },
    {
      "carryoverAmount": 13249,
      "carryover": "$13,249",
      "wagertype": "Pick 6",
      "track": "Finger Lakes",
      "date": "Oct 23",
      "ndate": 20231023
    },
    {
      "carryoverAmount": 11805,
      "carryover": "$11,805",
      "wagertype": "Super High Five",
      "track": "Keeneland",
      "date": "Oct 22",
      "ndate": 20231022
    },
    {
      "carryoverAmount": 10000,
      "carryover": "$10,000",
      "wagertype": "Pick 6",
      "track": "Los Alamitos",
      "date": "Oct 22",
      "ndate": 20231022
    },
    {
      "carryoverAmount": 3197,
      "carryover": "$3,197",
      "wagertype": "Super High Five",
      "track": "Gulfstream Park",
      "date": "Oct 22",
      "ndate": 20231022
    },
    {
      "carryoverAmount": 1803,
      "carryover": "$1,803",
      "wagertype": "Pick 6 Jackpot",
      "track": "Golden Gate",
      "date": "Oct 22",
      "ndate": 20231022
    },
    {
      "carryoverAmount": 1209,
      "carryover": "$1,209",
      "wagertype": "Pick 6 Jackpot",
      "track": "Laurel Park",
      "date": "Oct 22",
      "ndate": 20231022
    },
    {
      "carryoverAmount": 1069,
      "carryover": "$1,069",
      "wagertype": "Super High Five",
      "track": "Golden Gate",
      "date": "Oct 22",
      "ndate": 20231022
    },
    {
      "carryoverAmount": 1007,
      "carryover": "$1,007",
      "wagertype": "Super High Five",
      "track": "Golden Gate",
      "date": "Oct 22",
      "ndate": 20231022
    },
    {
      "carryoverAmount": 887,
      "carryover": "$887",
      "wagertype": "Pick 5",
      "track": "Presque Isle",
      "date": "Oct 23",
      "ndate": 20231023
    },
    {
      "carryoverAmount": 794,
      "carryover": "$794",
      "wagertype": "Super High Five Jackpot",
      "track": "Lone Star",
      "date": "Oct 26",
      "ndate": 20231026
    },
    {
      "carryoverAmount": 623,
      "carryover": "$623",
      "wagertype": "Pick 6",
      "track": "Lone Star",
      "date": "Oct 26",
      "ndate": 20231026
    },
    {
      "carryoverAmount": 618,
      "carryover": "$618",
      "wagertype": "Super High Five",
      "track": "Mountaineer",
      "date": "Oct 22",
      "ndate": 20231022
    },
    {
      "carryoverAmount": 515,
      "carryover": "$515",
      "wagertype": "Super High Five",
      "track": "Golden Gate",
      "date": "Oct 22",
      "ndate": 20231022
    },
    {
      "carryoverAmount": 318,
      "carryover": "$318",
      "wagertype": "Pick 6 Jackpot",
      "track": "Mahoning Valley",
      "date": "Oct 23",
      "ndate": 20231023
    }
  ]
}
