{
  "carryovers": [
    {
      "carryoverAmount": 311073,
      "carryover": "$311,073",
      "wagertype": "Jackpot High-5",
      "track": "Arlington",
      "date": "Sep 16",
      "ndate": 20210916
    },
    {
      "carryoverAmount": 299782,
      "carryover": "$299,782",
      "wagertype": "Jackpot High-5",
      "track": "Woodbine",
      "date": "Sep 16",
      "ndate": 20210916
    },
    {
      "carryoverAmount": 97269,
      "carryover": "$97,269",
      "wagertype": "Pick 5 Jackpot",
      "track": "Parx Racing",
      "date": "Sep 15",
      "ndate": 20210915
    },
    {
      "carryoverAmount": 90087,
      "carryover": "$90,087",
      "wagertype": "Pick 6 Jackpot",
      "track": "Woodbine",
      "date": "Sep 16",
      "ndate": 20210916
    },
    {
      "carryoverAmount": 51736,
      "carryover": "$51,736",
      "wagertype": "Pick 5 Jackpot",
      "track": "Prairie Meadows",
      "date": "Sep 17",
      "ndate": 20210917
    },
    {
      "carryoverAmount": 33408,
      "carryover": "$33,408",
      "wagertype": "Pick 6 Jackpot",
      "track": "Gulfstream Park",
      "date": "Sep 16",
      "ndate": 20210916
    },
    {
      "carryoverAmount": 29770,
      "carryover": "$29,770",
      "wagertype": "Pick 5 Jackpot",
      "track": "Louisiana Downs",
      "date": "Sep 18",
      "ndate": 20210918
    },
    {
      "carryoverAmount": 9462,
      "carryover": "$9,462",
      "wagertype": "Pick 5",
      "track": "Laurel Park",
      "date": "Sep 16",
      "ndate": 20210916
    },
    {
      "carryoverAmount": 7751,
      "carryover": "$7,751",
      "wagertype": "Pick 6 Jackpot",
      "track": "Golden Gate Fields",
      "date": "Sep 17",
      "ndate": 20210917
    },
    {
      "carryoverAmount": 4259,
      "carryover": "$4,259",
      "wagertype": "Pick 6 Jackpot",
      "track": "Laurel Park",
      "date": "Sep 16",
      "ndate": 20210916
    },
    {
      "carryoverAmount": 3933,
      "carryover": "$3,933",
      "wagertype": "Pick 6 Jackpot",
      "track": "Emerald Downs",
      "date": "Sep 18",
      "ndate": 20210918
    },
    {
      "carryoverAmount": 3862,
      "carryover": "$3,862",
      "wagertype": "Pick 7",
      "track": "Arlington",
      "date": "Sep 16",
      "ndate": 20210916
    },
    {
      "carryoverAmount": 2788,
      "carryover": "$2,788",
      "wagertype": "Super High Five",
      "track": "Golden Gate Fields",
      "date": "Sep 17",
      "ndate": 20210917
    },
    {
      "carryoverAmount": 2508,
      "carryover": "$2,508",
      "wagertype": "Super High Five",
      "track": "Gulfstream Park",
      "date": "Sep 16",
      "ndate": 20210916
    },
    {
      "carryoverAmount": 2135,
      "carryover": "$2,135",
      "wagertype": "Super High Five",
      "track": "Golden Gate Fields",
      "date": "Sep 17",
      "ndate": 20210917
    },
    {
      "carryoverAmount": 2079,
      "carryover": "$2,079",
      "wagertype": "Z-5 Super Hi-5",
      "track": "Laurel Park",
      "date": "Sep 16",
      "ndate": 20210916
    },
    {
      "carryoverAmount": 2058,
      "carryover": "$2,058",
      "wagertype": "Super High Five",
      "track": "Indiana Grand Race Course",
      "date": "Sep 15",
      "ndate": 20210915
    },
    {
      "carryoverAmount": 812,
      "carryover": "$812",
      "wagertype": "Pick 6 Jackpot",
      "track": "Thistledown",
      "date": "Sep 15",
      "ndate": 20210915
    },
    {
      "carryoverAmount": 474,
      "carryover": "$474",
      "wagertype": "Z-5 Super Hi-5",
      "track": "Laurel Park",
      "date": "Sep 16",
      "ndate": 20210916
    },
    {
      "carryoverAmount": 367,
      "carryover": "$367",
      "wagertype": "Z-5 Super Hi-5",
      "track": "Laurel Park",
      "date": "Sep 16",
      "ndate": 20210916
    },
    {
      "carryoverAmount": 208,
      "carryover": "$208",
      "wagertype": "Pick 5",
      "track": "Arapahoe Park",
      "date": "Sep 15",
      "ndate": 20210915
    }
  ]
}
