{
  "carryovers": [
    {
      "carryoverAmount": 2341707,
      "carryover": "$2,341,707",
      "wagertype": "Pick 6 Jackpot",
      "track": "Gulfstream Park",
      "date": "Jun 14",
      "ndate": 20190614
    },
    {
      "carryoverAmount": 1161294,
      "carryover": "$1,161,294",
      "wagertype": "Pick 6 Jackpot",
      "track": "Santa Anita",
      "date": "Jun 14",
      "ndate": 20190614
    },
    {
      "carryoverAmount": 151859,
      "carryover": "$151,859",
      "wagertype": "Pick 6 Jackpot",
      "track": "Churchill Downs",
      "date": "Jun 14",
      "ndate": 20190614
    },
    {
      "carryoverAmount": 65143,
      "carryover": "$65,143",
      "wagertype": "Super High Five Jackpot",
      "track": "Woodbine",
      "date": "Jun 14",
      "ndate": 20190614
    },
    {
      "carryoverAmount": 59757,
      "carryover": "$59,757",
      "wagertype": "Pick 6 Jackpot",
      "track": "Thistledown",
      "date": "Jun 15",
      "ndate": 20190615
    },
    {
      "carryoverAmount": 44961,
      "carryover": "$44,961",
      "wagertype": "Pick 6 Jackpot",
      "track": "Louisiana Downs",
      "date": "Jun 15",
      "ndate": 20190615
    },
    {
      "carryoverAmount": 32058,
      "carryover": "$32,058",
      "wagertype": "Pick 6",
      "track": "Belmont Park",
      "date": "Jun 14",
      "ndate": 20190614
    },
    {
      "carryoverAmount": 29029,
      "carryover": "$29,029",
      "wagertype": "Super High Five Jackpot",
      "track": "Arlington",
      "date": "Jun 14",
      "ndate": 20190614
    },
    {
      "carryoverAmount": 27568,
      "carryover": "$27,568",
      "wagertype": "Pick 6 Jackpot",
      "track": "Monmouth Park",
      "date": "Jun 14",
      "ndate": 20190614
    },
    {
      "carryoverAmount": 24239,
      "carryover": "$24,239",
      "wagertype": "Pick 5 Jackpot",
      "track": "Louisiana Downs",
      "date": "Jun 15",
      "ndate": 20190615
    },
    {
      "carryoverAmount": 17882,
      "carryover": "$17,882",
      "wagertype": "Super High Five",
      "track": "Churchill Downs",
      "date": "Jun 14",
      "ndate": 20190614
    },
    {
      "carryoverAmount": 14950,
      "carryover": "$14,950",
      "wagertype": "Pick 5",
      "track": "Mountaineer",
      "date": "Jun 16",
      "ndate": 20190616
    },
    {
      "carryoverAmount": 13503,
      "carryover": "$13,503",
      "wagertype": "Pick 5 Jackpot",
      "track": "Canterbury Park",
      "date": "Jun 14",
      "ndate": 20190614
    },
    {
      "carryoverAmount": 13351,
      "carryover": "$13,351",
      "wagertype": "Tri Super",
      "track": "Ruidoso Downs",
      "date": "Jun 14",
      "ndate": 20190614
    },
    {
      "carryoverAmount": 12739,
      "carryover": "$12,739",
      "wagertype": "Pick 5 Jackpot",
      "track": "Prairie Meadows",
      "date": "Jun 14",
      "ndate": 20190614
    },
    {
      "carryoverAmount": 12501,
      "carryover": "$12,501",
      "wagertype": "Pick 5",
      "track": "Assiniboia",
      "date": "Jun 14",
      "ndate": 20190614
    },
    {
      "carryoverAmount": 6803,
      "carryover": "$6,803",
      "wagertype": "Pick 7 Jackpot",
      "track": "Emerald Downs",
      "date": "Jun 14",
      "ndate": 20190614
    },
    {
      "carryoverAmount": 6787,
      "carryover": "$6,787",
      "wagertype": "Pick 6",
      "track": "Indiana Grand",
      "date": "Jun 14",
      "ndate": 20190614
    },
    {
      "carryoverAmount": 6455,
      "carryover": "$6,455",
      "wagertype": "Pick 6 Jackpot",
      "track": "Laurel Park",
      "date": "Jun 14",
      "ndate": 20190614
    },
    {
      "carryoverAmount": 6019,
      "carryover": "$6,019",
      "wagertype": "Super High Five Jackpot",
      "track": "Presque Isle",
      "date": "Jun 17",
      "ndate": 20190617
    },
    {
      "carryoverAmount": 4692,
      "carryover": "$4,692",
      "wagertype": "Super High Five Jackpot",
      "track": "Century Mile",
      "date": "Jun 15",
      "ndate": 20190615
    },
    {
      "carryoverAmount": 3647,
      "carryover": "$3,647",
      "wagertype": "Super High Five",
      "track": "Indiana Grand",
      "date": "Jun 14",
      "ndate": 20190614
    },
    {
      "carryoverAmount": 2333,
      "carryover": "$2,333",
      "wagertype": "Pick 6 Jackpot",
      "track": "Charles Town",
      "date": "Jun 14",
      "ndate": 20190614
    },
    {
      "carryoverAmount": 2258,
      "carryover": "$2,258",
      "wagertype": "Super High Five Jackpot",
      "track": "Assiniboia",
      "date": "Jun 14",
      "ndate": 20190614
    },
    {
      "carryoverAmount": 2211,
      "carryover": "$2,211",
      "wagertype": "Pick 6 Jackpot",
      "track": "Presque Isle",
      "date": "Jun 17",
      "ndate": 20190617
    },
    {
      "carryoverAmount": 1801,
      "carryover": "$1,801",
      "wagertype": "Pick 6 Jackpot",
      "track": "Lone Star",
      "date": "Jun 15",
      "ndate": 20190615
    },
    {
      "carryoverAmount": 1678,
      "carryover": "$1,678",
      "wagertype": "Pick 5",
      "track": "Century Mile",
      "date": "Jun 15",
      "ndate": 20190615
    },
    {
      "carryoverAmount": 1027,
      "carryover": "$1,027",
      "wagertype": "Pick 6 Jackpot",
      "track": "Penn National",
      "date": "Jun 14",
      "ndate": 20190614
    },
    {
      "carryoverAmount": 756,
      "carryover": "$756",
      "wagertype": "Pick 5",
      "track": "Arizona Downs",
      "date": "Jun 15",
      "ndate": 20190615
    },
    {
      "carryoverAmount": 666,
      "carryover": "$666",
      "wagertype": "Pick 5",
      "track": "Hastings",
      "date": "Jun 15",
      "ndate": 20190615
    },
    {
      "carryoverAmount": 472,
      "carryover": "$472",
      "wagertype": "Super High Five",
      "track": "Laurel Park",
      "date": "Jun 14",
      "ndate": 20190614
    },
    {
      "carryoverAmount": 435,
      "carryover": "$435",
      "wagertype": "Pick 4",
      "track": "Marquis Downs",
      "date": "Jun 14",
      "ndate": 20190614
    },
    {
      "carryoverAmount": 411,
      "carryover": "$411",
      "wagertype": "Superfecta",
      "track": "Marquis Downs",
      "date": "Jun 14",
      "ndate": 20190614
    }
  ]
}
