{
  "carryovers": [
    {
      "carryoverAmount": 130885,
      "carryover": "$130,885",
      "wagertype": "Super High Five Jackpot",
      "track": "Woodbine",
      "date": "Oct 06",
      "ndate": 20221006
    },
    {
      "carryoverAmount": 98692,
      "carryover": "$98,692",
      "wagertype": "Pick 6 Jackpot",
      "track": "Santa Anita",
      "date": "Oct 07",
      "ndate": 20221007
    },
    {
      "carryoverAmount": 78826,
      "carryover": "$78,826",
      "wagertype": "Pick 6 Jackpot",
      "track": "Charles Town",
      "date": "Oct 05",
      "ndate": 20221005
    },
    {
      "carryoverAmount": 71284,
      "carryover": "$71,284",
      "wagertype": "Pick 6",
      "track": "Belmont At The",
      "date": "Oct 06",
      "ndate": 20221006
    },
    {
      "carryoverAmount": 51682,
      "carryover": "$51,682",
      "wagertype": "Pick 6 Jackpot",
      "track": "Woodbine",
      "date": "Oct 06",
      "ndate": 20221006
    },
    {
      "carryoverAmount": 36004,
      "carryover": "$36,004",
      "wagertype": "Pick 6 Jackpot",
      "track": "Horseshoe",
      "date": "Oct 03",
      "ndate": 20221003
    },
    {
      "carryoverAmount": 28462,
      "carryover": "$28,462",
      "wagertype": "Pick 5 Jackpot",
      "track": "Parx Racing",
      "date": "Oct 03",
      "ndate": 20221003
    },
    {
      "carryoverAmount": 16951,
      "carryover": "$16,951",
      "wagertype": "Pick 6 Jackpot",
      "track": "Gulfstream Park",
      "date": "Oct 07",
      "ndate": 20221007
    },
    {
      "carryoverAmount": 16219,
      "carryover": "$16,219",
      "wagertype": "Pick 5",
      "track": "Mountaineer",
      "date": "Oct 03",
      "ndate": 20221003
    },
    {
      "carryoverAmount": 14148,
      "carryover": "$14,148",
      "wagertype": "Super High Five",
      "track": "Santa Anita",
      "date": "Oct 07",
      "ndate": 20221007
    },
    {
      "carryoverAmount": 5209,
      "carryover": "$5,209",
      "wagertype": "Super High Five Jackpot",
      "track": "Hawthorne",
      "date": "Oct 07",
      "ndate": 20221007
    },
    {
      "carryoverAmount": 3628,
      "carryover": "$3,628",
      "wagertype": "Super High Five",
      "track": "Santa Anita",
      "date": "Oct 07",
      "ndate": 20221007
    },
    {
      "carryoverAmount": 2229,
      "carryover": "$2,229",
      "wagertype": "Super High Five",
      "track": "Santa Anita",
      "date": "Oct 07",
      "ndate": 20221007
    },
    {
      "carryoverAmount": 2128,
      "carryover": "$2,128",
      "wagertype": "Super High Five",
      "track": "Gulfstream Park",
      "date": "Oct 07",
      "ndate": 20221007
    },
    {
      "carryoverAmount": 2113,
      "carryover": "$2,113",
      "wagertype": "Super High Five",
      "track": "Gulfstream Park",
      "date": "Oct 07",
      "ndate": 20221007
    },
    {
      "carryoverAmount": 2022,
      "carryover": "$2,022",
      "wagertype": "Pick 5",
      "track": "Lone Star",
      "date": "Oct 07",
      "ndate": 20221007
    },
    {
      "carryoverAmount": 1913,
      "carryover": "$1,913",
      "wagertype": "Pick 6 Jackpot",
      "track": "Laurel Park",
      "date": "Oct 06",
      "ndate": 20221006
    },
    {
      "carryoverAmount": 1886,
      "carryover": "$1,886",
      "wagertype": "Pick 5",
      "track": "Arapahoe",
      "date": "Oct 03",
      "ndate": 20221003
    },
    {
      "carryoverAmount": 1542,
      "carryover": "$1,542",
      "wagertype": "Super High Five",
      "track": "Gulfstream Park",
      "date": "Oct 07",
      "ndate": 20221007
    },
    {
      "carryoverAmount": 1468,
      "carryover": "$1,468",
      "wagertype": "Pick 6",
      "track": "Finger Lakes",
      "date": "Oct 03",
      "ndate": 20221003
    },
    {
      "carryoverAmount": 998,
      "carryover": "$998",
      "wagertype": "Pick 6",
      "track": "Lone Star",
      "date": "Oct 07",
      "ndate": 20221007
    },
    {
      "carryoverAmount": 593,
      "carryover": "$593",
      "wagertype": "Pick 5",
      "track": "Belterra Park",
      "date": "Oct 04",
      "ndate": 20221004
    },
    {
      "carryoverAmount": 569,
      "carryover": "$569",
      "wagertype": "Pick 6 Jackpot",
      "track": "Thistledown",
      "date": "Oct 03",
      "ndate": 20221003
    },
    {
      "carryoverAmount": 336,
      "carryover": "$336",
      "wagertype": "Pick 6 Jackpot",
      "track": "Hawthorne",
      "date": "Oct 07",
      "ndate": 20221007
    }
  ]
}
