{
  "carryovers": [
    {
      "carryoverAmount": 614171,
      "carryover": "$614,171",
      "wagertype": "Pick 6 Jackpot",
      "track": "Gulfstream Park",
      "date": "Mar 01",
      "ndate": 20240301
    },
    {
      "carryoverAmount": 46356,
      "carryover": "$46,356",
      "wagertype": "Pick 6 Jackpot",
      "track": "Turfway Park",
      "date": "Mar 01",
      "ndate": 20240301
    },
    {
      "carryoverAmount": 26890,
      "carryover": "$26,890",
      "wagertype": "Pick 5 Jackpot",
      "track": "Parx Racing",
      "date": "Mar 04",
      "ndate": 20240304
    },
    {
      "carryoverAmount": 20154,
      "carryover": "$20,154",
      "wagertype": "Pick 5 Jackpot",
      "track": "Parx Racing",
      "date": "Mar 04",
      "ndate": 20240304
    },
    {
      "carryoverAmount": 19434,
      "carryover": "$19,434",
      "wagertype": "Pick 6 Jackpot",
      "track": "Tampa Bay",
      "date": "Mar 01",
      "ndate": 20240301
    },
    {
      "carryoverAmount": 10758,
      "carryover": "$10,758",
      "wagertype": "Super High Five",
      "track": "Turfway Park",
      "date": "Mar 01",
      "ndate": 20240301
    },
    {
      "carryoverAmount": 10679,
      "carryover": "$10,679",
      "wagertype": "Pick 6 Jackpot",
      "track": "Charles Town",
      "date": "Mar 01",
      "ndate": 20240301
    },
    {
      "carryoverAmount": 4239,
      "carryover": "$4,239",
      "wagertype": "Pick 6",
      "track": "Fair Grounds",
      "date": "Mar 01",
      "ndate": 20240301
    },
    {
      "carryoverAmount": 3221,
      "carryover": "$3,221",
      "wagertype": "Pick 6 Jackpot",
      "track": "Laurel Park",
      "date": "Mar 01",
      "ndate": 20240301
    },
    {
      "carryoverAmount": 2616,
      "carryover": "$2,616",
      "wagertype": "Super High Five Jackpot",
      "track": "Penn National",
      "date": "Mar 01",
      "ndate": 20240301
    },
    {
      "carryoverAmount": 2130,
      "carryover": "$2,130",
      "wagertype": "Super High Five Jackpot",
      "track": "Sam Houston",
      "date": "Mar 01",
      "ndate": 20240301
    },
    {
      "carryoverAmount": 1438,
      "carryover": "$1,438",
      "wagertype": "Pick 5",
      "track": "Sunland Park",
      "date": "Mar 01",
      "ndate": 20240301
    },
    {
      "carryoverAmount": 1236,
      "carryover": "$1,236",
      "wagertype": "Super High Five",
      "track": "Sunland Park",
      "date": "Mar 01",
      "ndate": 20240301
    },
    {
      "carryoverAmount": 776,
      "carryover": "$776",
      "wagertype": "Pick 5",
      "track": "Fonner Park",
      "date": "Mar 01",
      "ndate": 20240301
    }
  ]
}
