{
  "carryovers": [
    {
      "carryoverAmount": 2568043,
      "carryover": "$2,568,043",
      "wagertype": "Pick 6 Jackpot",
      "track": "Gulfstream Park",
      "date": "Jan 17",
      "ndate": 20200117
    },
    {
      "carryoverAmount": 432042,
      "carryover": "$432,042",
      "wagertype": "Pick 6 Jackpot",
      "track": "Santa Anita",
      "date": "Jan 17",
      "ndate": 20200117
    },
    {
      "carryoverAmount": 208660,
      "carryover": "$208,660",
      "wagertype": "Pick 5 Jackpot",
      "track": "Fair Grounds",
      "date": "Jan 17",
      "ndate": 20200117
    },
    {
      "carryoverAmount": 113745,
      "carryover": "$113,745",
      "wagertype": "Pick 6 Jackpot",
      "track": "Aqueduct",
      "date": "Jan 17",
      "ndate": 20200117
    },
    {
      "carryoverAmount": 16318,
      "carryover": "$16,318",
      "wagertype": "Pick 6",
      "track": "Tampa Bay",
      "date": "Jan 17",
      "ndate": 20200117
    },
    {
      "carryoverAmount": 5940,
      "carryover": "$5,940",
      "wagertype": "Pick 6 Jackpot",
      "track": "Turf Paradise",
      "date": "Jan 18",
      "ndate": 20200118
    },
    {
      "carryoverAmount": 4406,
      "carryover": "$4,406",
      "wagertype": "Super High Five",
      "track": "Sam Houston",
      "date": "Jan 17",
      "ndate": 20200117
    },
    {
      "carryoverAmount": 3239,
      "carryover": "$3,239",
      "wagertype": "Super High Five Jackpot",
      "track": "Penn National",
      "date": "Jan 17",
      "ndate": 20200117
    },
    {
      "carryoverAmount": 3097,
      "carryover": "$3,097",
      "wagertype": "Pick 6 Jackpot",
      "track": "Mahoning Valley",
      "date": "Jan 18",
      "ndate": 20200118
    },
    {
      "carryoverAmount": 2900,
      "carryover": "$2,900",
      "wagertype": "Super High Five",
      "track": "Turfway Park",
      "date": "Jan 17",
      "ndate": 20200117
    },
    {
      "carryoverAmount": 2417,
      "carryover": "$2,417",
      "wagertype": "Pick 6 Jackpot",
      "track": "Golden Gate",
      "date": "Jan 17",
      "ndate": 20200117
    },
    {
      "carryoverAmount": 2359,
      "carryover": "$2,359",
      "wagertype": "Pick 5",
      "track": "Penn National",
      "date": "Jan 17",
      "ndate": 20200117
    },
    {
      "carryoverAmount": 2358,
      "carryover": "$2,358",
      "wagertype": "Pick 6 Jackpot",
      "track": "Sam Houston",
      "date": "Jan 17",
      "ndate": 20200117
    },
    {
      "carryoverAmount": 1395,
      "carryover": "$1,395",
      "wagertype": "Super High Five",
      "track": "Golden Gate",
      "date": "Jan 17",
      "ndate": 20200117
    },
    {
      "carryoverAmount": 1254,
      "carryover": "$1,254",
      "wagertype": "Pick 6 Jackpot",
      "track": "Charles Town",
      "date": "Jan 17",
      "ndate": 20200117
    },
    {
      "carryoverAmount": 696,
      "carryover": "$696",
      "wagertype": "Pick 6 Jackpot",
      "track": "Turfway Park",
      "date": "Jan 17",
      "ndate": 20200117
    }
  ]
}
