{
  "carryovers": [
    {
      "carryoverAmount": 662512,
      "carryover": "$662,512",
      "wagertype": "Pick 6 Jackpot",
      "track": "Santa Anita Park",
      "date": "Oct 21",
      "ndate": 20181021
    },
    {
      "carryoverAmount": 86095,
      "carryover": "$86,095",
      "wagertype": "Pick 5",
      "track": "Gulfstream Park West",
      "date": "Oct 21",
      "ndate": 20181021
    },
    {
      "carryoverAmount": 46365,
      "carryover": "$46,365",
      "wagertype": "Pick 6 Jackpot",
      "track": "Gulfstream Park West",
      "date": "Oct 21",
      "ndate": 20181021
    },
    {
      "carryoverAmount": 37308,
      "carryover": "$37,308",
      "wagertype": "Pick 6",
      "track": "Belmont Park",
      "date": "Oct 21",
      "ndate": 20181021
    },
    {
      "carryoverAmount": 15118,
      "carryover": "$15,118",
      "wagertype": "Pick 6",
      "track": "Los Alamitos",
      "date": "Oct 21",
      "ndate": 20181021
    },
    {
      "carryoverAmount": 14517,
      "carryover": "$14,517",
      "wagertype": "Jackpot High-5",
      "track": "Hawthorne",
      "date": "Oct 24",
      "ndate": 20181024
    },
    {
      "carryoverAmount": 13203,
      "carryover": "$13,203",
      "wagertype": "Super High Five",
      "track": "Century Downs",
      "date": "Oct 21",
      "ndate": 20181021
    },
    {
      "carryoverAmount": 12655,
      "carryover": "$12,655",
      "wagertype": "Jackpot High-5",
      "track": "Penn National",
      "date": "Oct 24",
      "ndate": 20181024
    },
    {
      "carryoverAmount": 12250,
      "carryover": "$12,250",
      "wagertype": "Pick 6",
      "track": "Remington Park",
      "date": "Oct 24",
      "ndate": 20181024
    },
    {
      "carryoverAmount": 11638,
      "carryover": "$11,638",
      "wagertype": "Jackpot High-5",
      "track": "Woodbine",
      "date": "Oct 21",
      "ndate": 20181021
    },
    {
      "carryoverAmount": 10576,
      "carryover": "$10,576",
      "wagertype": "Pick 6",
      "track": "Keeneland",
      "date": "Oct 21",
      "ndate": 20181021
    },
    {
      "carryoverAmount": 10186,
      "carryover": "$10,186",
      "wagertype": "Z-5 Super Hi-5",
      "track": "Gulfstream Park West",
      "date": "Oct 21",
      "ndate": 20181021
    },
    {
      "carryoverAmount": 8598,
      "carryover": "$8,598",
      "wagertype": "Pick 6 Jackpot",
      "track": "Hollywood Casino At Charles To",
      "date": "Oct 25",
      "ndate": 20181025
    },
    {
      "carryoverAmount": 7902,
      "carryover": "$7,902",
      "wagertype": "Pick 6 Jackpot",
      "track": "Hawthorne",
      "date": "Oct 24",
      "ndate": 20181024
    },
    {
      "carryoverAmount": 7016,
      "carryover": "$7,016",
      "wagertype": "Pick 6 Jackpot",
      "track": "Laurel Park",
      "date": "Oct 21",
      "ndate": 20181021
    },
    {
      "carryoverAmount": 6721,
      "carryover": "$6,721",
      "wagertype": "Z-5 Super Hi-5",
      "track": "Keeneland",
      "date": "Oct 21",
      "ndate": 20181021
    },
    {
      "carryoverAmount": 5867,
      "carryover": "$5,867",
      "wagertype": "Super High Five",
      "track": "Golden Gate Fields",
      "date": "Oct 21",
      "ndate": 20181021
    },
    {
      "carryoverAmount": 5500,
      "carryover": "$5,500",
      "wagertype": "Z-5 Super Hi-5",
      "track": "Gulfstream Park West",
      "date": "Oct 21",
      "ndate": 20181021
    },
    {
      "carryoverAmount": 4862,
      "carryover": "$4,862",
      "wagertype": "Pick 6 Jackpot",
      "track": "Golden Gate Fields",
      "date": "Oct 21",
      "ndate": 20181021
    },
    {
      "carryoverAmount": 4533,
      "carryover": "$4,533",
      "wagertype": "Pick 6 Jackpot",
      "track": "Lone Star Park",
      "date": "Oct 26",
      "ndate": 20181026
    },
    {
      "carryoverAmount": 3508,
      "carryover": "$3,508",
      "wagertype": "Z-5 Super Hi-5",
      "track": "Gulfstream Park West",
      "date": "Oct 21",
      "ndate": 20181021
    },
    {
      "carryoverAmount": 2576,
      "carryover": "$2,576",
      "wagertype": "Super High Five",
      "track": "Zia Park",
      "date": "Oct 21",
      "ndate": 20181021
    },
    {
      "carryoverAmount": 2506,
      "carryover": "$2,506",
      "wagertype": "Super High Five",
      "track": "Golden Gate Fields",
      "date": "Oct 21",
      "ndate": 20181021
    },
    {
      "carryoverAmount": 1914,
      "carryover": "$1,914",
      "wagertype": "Z-5 Super Hi-5",
      "track": "Keeneland",
      "date": "Oct 21",
      "ndate": 20181021
    },
    {
      "carryoverAmount": 1719,
      "carryover": "$1,719",
      "wagertype": "Super High Five",
      "track": "Mountaineer Casino Racetrack",
      "date": "Oct 21",
      "ndate": 20181021
    },
    {
      "carryoverAmount": 1635,
      "carryover": "$1,635",
      "wagertype": "Pick 5",
      "track": "Finger Lakes",
      "date": "Oct 22",
      "ndate": 20181022
    },
    {
      "carryoverAmount": 1559,
      "carryover": "$1,559",
      "wagertype": "Z-5 Super Hi-5",
      "track": "Gulfstream Park West",
      "date": "Oct 21",
      "ndate": 20181021
    },
    {
      "carryoverAmount": 1523,
      "carryover": "$1,523",
      "wagertype": "Pick 5",
      "track": "Turf Paradise",
      "date": "Oct 21",
      "ndate": 20181021
    },
    {
      "carryoverAmount": 1513,
      "carryover": "$1,513",
      "wagertype": "Z-5 Super Hi-5",
      "track": "Gulfstream Park West",
      "date": "Oct 21",
      "ndate": 20181021
    },
    {
      "carryoverAmount": 1361,
      "carryover": "$1,361",
      "wagertype": "Z-5 Super Hi-5",
      "track": "Keeneland",
      "date": "Oct 21",
      "ndate": 20181021
    },
    {
      "carryoverAmount": 1220,
      "carryover": "$1,220",
      "wagertype": "Super High Five",
      "track": "Golden Gate Fields",
      "date": "Oct 21",
      "ndate": 20181021
    },
    {
      "carryoverAmount": 1071,
      "carryover": "$1,071",
      "wagertype": "Z-5 Super Hi-5",
      "track": "Gulfstream Park West",
      "date": "Oct 21",
      "ndate": 20181021
    },
    {
      "carryoverAmount": 1059,
      "carryover": "$1,059",
      "wagertype": "Z-5 Super Hi-5",
      "track": "Keeneland",
      "date": "Oct 21",
      "ndate": 20181021
    },
    {
      "carryoverAmount": 718,
      "carryover": "$718",
      "wagertype": "Super High Five",
      "track": "Golden Gate Fields",
      "date": "Oct 21",
      "ndate": 20181021
    }
  ]
}
