{
  "carryovers": [
    {
      "carryoverAmount": 4415,
      "carryover": "$4,415",
      "wagertype": "Pick 5 Jackpot",
      "track": "Louisiana Downs",
      "date": "May 07",
      "ndate": 20190507
    },
    {
      "carryoverAmount": 3045,
      "carryover": "$3,045",
      "wagertype": "Pick 6 Jackpot",
      "track": "Thistledown",
      "date": "May 07",
      "ndate": 20190507
    },
    {
      "carryoverAmount": 1297,
      "carryover": "$1,297",
      "wagertype": "Super High Five",
      "track": "Mountaineer Casino Racetrack",
      "date": "May 07",
      "ndate": 20190507
    },
    {
      "carryoverAmount": 1087,
      "carryover": "$1,087",
      "wagertype": "Pick 6 Jackpot",
      "track": "Sam Houston Race Park",
      "date": "May 10",
      "ndate": 20190510
    },
    {
      "carryoverAmount": 1006,
      "carryover": "$1,006",
      "wagertype": "Pick 5",
      "track": "Sam Houston Race Park",
      "date": "May 10",
      "ndate": 20190510
    },
    {
      "carryoverAmount": 590,
      "carryover": "$590",
      "wagertype": "Z-5 Super Hi-5",
      "track": "Sam Houston Race Park",
      "date": "May 10",
      "ndate": 20190510
    }
  ]
}
